odoo8_addon_sale_owner_stock_sourcing-8.0.0.1.0.99.dev18-py3.8-nspkg.pth
odoo_addons/sale_owner_stock_sourcing/README.rst
odoo_addons/sale_owner_stock_sourcing/__init__.py
odoo_addons/sale_owner_stock_sourcing/__openerp__.py
odoo_addons/sale_owner_stock_sourcing/i18n/ca.po
odoo_addons/sale_owner_stock_sourcing/i18n/de.po
odoo_addons/sale_owner_stock_sourcing/i18n/es.po
odoo_addons/sale_owner_stock_sourcing/i18n/es_MX.po
odoo_addons/sale_owner_stock_sourcing/i18n/fr.po
odoo_addons/sale_owner_stock_sourcing/i18n/hr.po
odoo_addons/sale_owner_stock_sourcing/i18n/it.po
odoo_addons/sale_owner_stock_sourcing/i18n/nl_NL.po
odoo_addons/sale_owner_stock_sourcing/i18n/pt_BR.po
odoo_addons/sale_owner_stock_sourcing/i18n/pt_PT.po
odoo_addons/sale_owner_stock_sourcing/i18n/ro.po
odoo_addons/sale_owner_stock_sourcing/i18n/sale_owner_stock_sourcing.pot
odoo_addons/sale_owner_stock_sourcing/i18n/sk.po
odoo_addons/sale_owner_stock_sourcing/i18n/sl.po
odoo_addons/sale_owner_stock_sourcing/i18n/tr.po
odoo_addons/sale_owner_stock_sourcing/i18n/tr_TR.po
odoo_addons/sale_owner_stock_sourcing/i18n/zh_CN.po
odoo_addons/sale_owner_stock_sourcing/model/__init__.py
odoo_addons/sale_owner_stock_sourcing/model/procurement.py
odoo_addons/sale_owner_stock_sourcing/model/sale_order.py
odoo_addons/sale_owner_stock_sourcing/security/group.xml
odoo_addons/sale_owner_stock_sourcing/static/description/icon.png
odoo_addons/sale_owner_stock_sourcing/tests/__init__.py
odoo_addons/sale_owner_stock_sourcing/tests/test_int_sale_to_reservation.py
odoo_addons/sale_owner_stock_sourcing/tests/test_propagate_owner_to_move.py
odoo_addons/sale_owner_stock_sourcing/view/sale_order.xml
odoo8_addon_sale_owner_stock_sourcing-8.0.0.1.0.99.dev18.dist-info/METADATA
odoo8_addon_sale_owner_stock_sourcing-8.0.0.1.0.99.dev18.dist-info/WHEEL
odoo8_addon_sale_owner_stock_sourcing-8.0.0.1.0.99.dev18.dist-info/namespace_packages.txt
odoo8_addon_sale_owner_stock_sourcing-8.0.0.1.0.99.dev18.dist-info/top_level.txt
odoo8_addon_sale_owner_stock_sourcing-8.0.0.1.0.99.dev18.dist-info/RECORD
